{
    "partArray": [
        {
            "id": "text1",
            "colorHex": "#000000",
            "flags": 2048,
            "text": "Modern thought has realized considerable progress by reducing the existent to the series of appearances which manifest it. Its aim was to overcome a certain number of dualisms which have embarassed philosophy and to replace them by the monism of the phenomenon. There is no longer an exterior for the existent if one means by that a superficial covering which hides from sight the true nature of the object.",
            "font": "bluescreen"
        }
    ]
}
